setup.py
py_adyen/__init__.py
py_adyen/adyen.py
py_adyen/api.py
py_adyen/forms.py
py_adyen/notifications.py
py_adyen/settings.py
py_adyen/utils.py
py_adyen.egg-info/PKG-INFO
py_adyen.egg-info/SOURCES.txt
py_adyen.egg-info/dependency_links.txt
py_adyen.egg-info/top_level.txt