Metadata-Version: 1.0
Name: py-adyen
Version: 0.1.4
Summary: Python/Django interface to the Adyen payment gateway.
Home-page: http://github.com/svdgraaf/py-adyen/
Author: Sander van de Graaf
Author-email: mail@svdgraaf.nl
License:                     GNU GENERAL PUBLIC LICENSE
